MANIFEST.in
requirements.txt
setup.py
Mensajes/__init__.py
Mensajes.egg-info/PKG-INFO
Mensajes.egg-info/SOURCES.txt
Mensajes.egg-info/dependency_links.txt
Mensajes.egg-info/requires.txt
Mensajes.egg-info/top_level.txt
Mensajes/adios/__init__.py
Mensajes/adios/despedida.py
Mensajes/hola/Saludos.py
Mensajes/hola/__init__.py
tests/__init__.py
tests/test_hola.py