Metadata-Version: 1.0
Name: Mensajes
Version: 3.0
Summary: un paquete para saludar y despedir
Home-page: https://www.hektor.dev
Author: jhonatan Rincon
Author-email: jeramix92@gmail.com
License: UNKNOWN
Platform: UNKNOWN
